libcasm/clexmonte/_FixedConfigGenerator.py
libcasm/clexmonte/_IncrementalConditionsStateGenerator.py
libcasm/clexmonte/_MonteCalculator.py
libcasm/clexmonte/_RunData.py
libcasm/clexmonte/__init__.py
libcasm/clexmonte/_auto_configuration.py
libcasm/clexmonte/_clexmonte_functions.cpython-310-x86_64-linux-gnu.so
libcasm/clexmonte/_clexmonte_monte_calculator.cpython-310-x86_64-linux-gnu.so
libcasm/clexmonte/_clexmonte_run_management.cpython-310-x86_64-linux-gnu.so
libcasm/clexmonte/_clexmonte_state.cpython-310-x86_64-linux-gnu.so
libcasm/clexmonte/_clexmonte_system.cpython-310-x86_64-linux-gnu.so
libcasm/clexmonte/_system_methods.py
libcasm/clexmonte/parsing.py
libcasm/clexmonte/misc/__init__.py
libcasm/clexmonte/misc/contexts.py
libcasm/clexmonte/site_iterators/__init__.py
libcasm/clexmonte/site_iterators/_site_iterators.py
libcasm/include/casm/clexmonte/definitions.hh
libcasm/include/casm/clexmonte/canonical/canonical.hh
libcasm/include/casm/clexmonte/canonical/canonical_impl.hh
libcasm/include/casm/clexmonte/canonical/canonical_json_io.hh
libcasm/include/casm/clexmonte/events/AllowedEventList.hh
libcasm/include/casm/clexmonte/events/CompleteEventList.hh
libcasm/include/casm/clexmonte/events/ImpactTable.hh
libcasm/include/casm/clexmonte/events/event_data.hh
libcasm/include/casm/clexmonte/events/event_methods.hh
libcasm/include/casm/clexmonte/events/lotto.hh
libcasm/include/casm/clexmonte/events/io/json/event_data_json_io.hh
libcasm/include/casm/clexmonte/events/io/stream/EventState_stream_io.hh
libcasm/include/casm/clexmonte/events/lotto/event_rate_tree.hpp
libcasm/include/casm/clexmonte/events/lotto/event_rate_tree_impl.hpp
libcasm/include/casm/clexmonte/events/lotto/event_selector.hpp
libcasm/include/casm/clexmonte/events/lotto/random.hpp
libcasm/include/casm/clexmonte/events/lotto/rejection.hpp
libcasm/include/casm/clexmonte/events/lotto/rejection_free.hpp
libcasm/include/casm/clexmonte/events/lotto/sum_tree.hpp
libcasm_clexmonte-2.3.0.dist-info/licenses/LICENSE
libcasm_clexmonte-2.3.0.dist-info/METADATA
libcasm_clexmonte-2.3.0.dist-info/WHEEL
libcasm_clexmonte-2.3.0.dist-info/top_level.txt
libcasm_clexmonte-2.3.0.dist-info/RECORD
